README.md
setup.py
ephesus/__init__.py
ephesus/alle.py
ephesus/alleesti.py
ephesus/alleevol.py
ephesus/allenest.py
ephesus/allenestplot.py
ephesus/alleplot.py
ephesus/util.py
ephesus.egg-info/PKG-INFO
ephesus.egg-info/SOURCES.txt
ephesus.egg-info/dependency_links.txt
ephesus.egg-info/top_level.txt